ums/__init__.py
ums/__main__.py
ums/ums_main.py
ums-0.3.0.dist-info/LICENCE
ums-0.3.0.dist-info/METADATA
ums-0.3.0.dist-info/WHEEL
ums-0.3.0.dist-info/top_level.txt
ums-0.3.0.dist-info/RECORD
