Metadata-Version: 2.1
Name: ums
Version: 0.3.0
Summary: LPU UMS api for extracting user data like Profile, annoucement, messages, Timetable, Grades etc.
Home-page: https://github.com/knight-byte/Ums
Author: Abunachar Yeahhia
Author-email: abunachar1236@gmail.com
License: MIT
Download-URL: https://github.com/knight-byte/Ums/archive/v0.3.0.tar.gz
Keywords: lpu ums,ums,student,university management system,university,lpu
Platform: UNKNOWN
Classifier: Intended Audience :: Developers
Classifier: License :: OSI Approved :: MIT License
Classifier: Programming Language :: Python :: 3
License-File: LICENCE
Requires-Dist: bs4
Requires-Dist: requests
Requires-Dist: lxml
